optimal_guide_finder/__init__.py
optimal_guide_finder/cas_model.py
optimal_guide_finder/guide_finder.py
optimal_guide_finder/guide_generator.py
optimal_guide_finder/guide_strength_calculator.py
optimal_guide_finder/memory_limit.py
optimal_guide_finder/Azimuth_Model/__init__.py
optimal_guide_finder/Azimuth_Model/cli_run_model.py
optimal_guide_finder/Azimuth_Model/cluster_job.py
optimal_guide_finder/Azimuth_Model/corrstats.py
optimal_guide_finder/Azimuth_Model/load_data.py
optimal_guide_finder/Azimuth_Model/local_multiprocessing.py
optimal_guide_finder/Azimuth_Model/metrics.py
optimal_guide_finder/Azimuth_Model/model_comparison.py
optimal_guide_finder/Azimuth_Model/predict.py
optimal_guide_finder/Azimuth_Model/util.py
optimal_guide_finder/Azimuth_Model/features/__init__.py
optimal_guide_finder/Azimuth_Model/features/featurization.py
optimal_guide_finder/Azimuth_Model/features/microhomology.py
optimal_guide_finder/Azimuth_Model/models/DNN.py
optimal_guide_finder/Azimuth_Model/models/GP.py
optimal_guide_finder/Azimuth_Model/models/__init__.py
optimal_guide_finder/Azimuth_Model/models/baselines.py
optimal_guide_finder/Azimuth_Model/models/ensembles.py
optimal_guide_finder/Azimuth_Model/models/gpy_ssk.py
optimal_guide_finder/Azimuth_Model/models/regression.py
optimal_guide_finder/Azimuth_Model/models/ssk.py
optimal_guide_finder/Azimuth_Model/saved_models/V3_model_full.pickle
optimal_guide_finder/Azimuth_Model/saved_models/V3_model_nopos.pickle
optimal_guide_finder/data/InvitroModel.mat
sgRNAble-1.0.12.dist-info/LICENSE
sgRNAble-1.0.12.dist-info/METADATA
sgRNAble-1.0.12.dist-info/WHEEL
sgRNAble-1.0.12.dist-info/entry_points.txt
sgRNAble-1.0.12.dist-info/top_level.txt
sgRNAble-1.0.12.dist-info/RECORD
