Metadata-Version: 2.1
Name: sgRNAble
Version: 1.0.12
Summary: CRISPR-Cas9 single guide RNA generation tool
Home-page: https://github.com/hallamlab/sgRNAble
Author: Avery Noonan, Siddarth Raghuvanshi, Ahmed Abdelmoneim
Author-email: sidr97@gmail.com
License: UNKNOWN
Platform: UNKNOWN
Classifier: Programming Language :: Python :: 3
Classifier: Operating System :: OS Independent
Requires-Python: ==3.7.*
Requires-Dist: biopython
Requires-Dist: matplotlib
Requires-Dist: numba
Requires-Dist: numpy
Requires-Dist: pandas
Requires-Dist: psutil
Requires-Dist: scikit-learn (==0.20.4)
Requires-Dist: scipy
Requires-Dist: tqdm
